pulp_2to3_migration/__init__.py
pulp_2to3_migration/exceptions.py
pulp_2to3_migration/app/__init__.py
pulp_2to3_migration/app/constants.py
pulp_2to3_migration/app/json_schema.py
pulp_2to3_migration/app/migration.py
pulp_2to3_migration/app/pre_migration.py
pulp_2to3_migration/app/serializers.py
pulp_2to3_migration/app/settings.py
pulp_2to3_migration/app/viewsets.py
pulp_2to3_migration/app/migrations/0001_initial.py
pulp_2to3_migration/app/migrations/0002_remove_pulp2distributor_pulp2_auto_publish.py
pulp_2to3_migration/app/migrations/0003_pulp2lazycatalog_indices.py
pulp_2to3_migration/app/migrations/0004_modularity_metafile_erratum_rpm.py
pulp_2to3_migration/app/migrations/0005_pulp2distribution.py
pulp_2to3_migration/app/migrations/0006_pulp2_comps.py
pulp_2to3_migration/app/migrations/0007_pulp2repository_pulp3_repository.py
pulp_2to3_migration/app/migrations/0008_pulp2srpm.py
pulp_2to3_migration/app/migrations/0009_pulp2erratum_allow_null.py
pulp_2to3_migration/app/migrations/0010_pulp2lazycatalog_is_migrated.py
pulp_2to3_migration/app/migrations/0011_lce_revision.py
pulp_2to3_migration/app/migrations/0012_size_bigint.py
pulp_2to3_migration/app/migrations/0013_fix_file_remote_migration.py
pulp_2to3_migration/app/migrations/0014_gzip_repodata.py
pulp_2to3_migration/app/migrations/0015_add_created_updated.py
pulp_2to3_migration/app/migrations/0016_type_index.py
pulp_2to3_migration/app/migrations/0017_pulp2debpackage.py
pulp_2to3_migration/app/migrations/0018_pulp2distributor_pulp2_repos.py
pulp_2to3_migration/app/migrations/0019_remove_pulp2_repository.py
pulp_2to3_migration/app/migrations/0020_fix_defaults.py
pulp_2to3_migration/app/migrations/0021_pulp2content_add_subid.py
pulp_2to3_migration/app/migrations/0022_add_structured_deb_types.py
pulp_2to3_migration/app/migrations/0023_remove_pulp2importer_repo_field.py
pulp_2to3_migration/app/migrations/0024_reposetup.py
pulp_2to3_migration/app/migrations/0025_remove_p2content_dups.py
pulp_2to3_migration-0.17.0.dist-info/LICENSE
pulp_2to3_migration-0.17.0.dist-info/METADATA
pulp_2to3_migration-0.17.0.dist-info/WHEEL
pulp_2to3_migration-0.17.0.dist-info/entry_points.txt
pulp_2to3_migration-0.17.0.dist-info/top_level.txt
pulp_2to3_migration-0.17.0.dist-info/RECORD
