Metadata-Version: 2.1
Name: pulp-2to3-migration
Version: 0.17.0
Summary: Pulp 2 to Pulp 3 migration tool
Home-page: http://www.pulpproject.org
Author: Pulp Team
Author-email: pulp-list@redhat.com
License: GPLv2+
Platform: UNKNOWN
Classifier: License :: OSI Approved :: GNU General Public License v2 or later (GPLv2+)
Classifier: Operating System :: POSIX :: Linux
Classifier: Framework :: Django
Classifier: Programming Language :: Python
Classifier: Programming Language :: Python :: 3
Classifier: Programming Language :: Python :: 3.8
Classifier: Programming Language :: Python :: 3.9
Requires-Python: >=3.8
Requires-Dist: pulpcore (<3.20,>=3.18.0)
Requires-Dist: pymongo (<4.0)
Requires-Dist: mongoengine (~=0.20)
Requires-Dist: semantic-version (<2.11,>=2.8)
Requires-Dist: jsonschema (~=4.4)
